pytoolsmith/__init__.py
pytoolsmith/batch_tool.py
pytoolsmith/tool_definition.py
pytoolsmith/tool_library.py
pytoolsmith/tool_parameters.py
pytoolsmith/utils.py
pytoolsmith/pytoolsmith_config/__init__.py
pytoolsmith/pytoolsmith_config/batch_runner.py
pytoolsmith/pytoolsmith_config/mappings.py
pytoolsmith/pytoolsmith_config/serialization.py
pytoolsmith/types/anthropic_types.py
pytoolsmith/types/bedrock_types.py
pytoolsmith/types/gemini_types.py
pytoolsmith/types/openai_types.py
pytoolsmith-1.0.0.data/data/CHANGELOG.md
pytoolsmith-1.0.0.dist-info/METADATA
pytoolsmith-1.0.0.dist-info/WHEEL
pytoolsmith-1.0.0.dist-info/licenses/LICENSE
pytoolsmith-1.0.0.dist-info/RECORD
