Metadata-Version: 2.4
Name: pytoolsmith
Version: 1.0.0
Summary: A lightweight Python library that simplifies the process of exposing functions as tools for Large Language Models
Project-URL: Homepage, https://github.com/zachrobo1/pytoolsmith
Project-URL: Bug Tracker, https://github.com/zachrobo1/pytoolsmith/issues
Author-email: Zach Cloud <me@zachb.cloud>
License: MIT
License-File: LICENSE
Classifier: License :: OSI Approved :: MIT License
Classifier: Operating System :: OS Independent
Classifier: Programming Language :: Python :: 3
Requires-Python: >=3.11
